retroflux/BacktestRunner.py
retroflux/BacktestVisualizer.py
retroflux/PortfolioConfigLoader.py
retroflux/PortfolioDataFetcher.py
retroflux/__init__.py
retroflux/main.py
medor_retroflux-1.1.0.dist-info/LICENSE.txt
medor_retroflux-1.1.0.dist-info/METADATA
medor_retroflux-1.1.0.dist-info/WHEEL
medor_retroflux-1.1.0.dist-info/entry_points.txt
medor_retroflux-1.1.0.dist-info/top_level.txt
medor_retroflux-1.1.0.dist-info/RECORD
