Metadata-Version: 2.1
Name: medor-retroflux
Version: 1.1.0
Summary: A backtesting tool for financial strategies
Home-page: https://github.com/Medor-Inc/Retroflux.git
Author: Vince BI Miao
Author-email: miao.vince.bi@medor.ca
Classifier: Programming Language :: Python :: 3
Classifier: License :: OSI Approved :: GNU Affero General Public License v3
Classifier: Operating System :: OS Independent
Requires-Python: >=3.8
License-File: LICENSE.txt
Requires-Dist: pandas
Requires-Dist: matplotlib
Requires-Dist: pyyaml
Requires-Dist: numpy
Requires-Dist: plotly
Requires-Dist: yfinance
Requires-Dist: kaleido
Requires-Dist: openpyxl
Requires-Dist: nbformat
